{
  "1099247282": {
    "user_id": 1099247282,
    "username": "ars_1_k",
    "first_name": "Арсений",
    "last_name": "Ильинковский",
    "registered_at": "2026-01-04T14:43:46.211401",
    "last_active": "2026-01-04T14:43:46.211407",
    "streak_days": 0,
    "total_experience": 0,
    "completed_today": false,
    "last_completed_date": null,
    "notification_times": [
      "14:45",
      "15:45",
      "16:45"
    ],
    "notifications_enabled": true,
    "current_course": "speech",
    "course_experience": {
      "speech": 0
    }
  }
}